neon_transformers/__init__.py
neon_transformers/audio_transformers.py
neon_transformers/metadata_transformers.py
neon_transformers/streams.py
neon_transformers/tasks.py
neon_transformers/text_transformers.py
neon_transformers-1.0.0.dist-info/LICENSE.md
neon_transformers-1.0.0.dist-info/METADATA
neon_transformers-1.0.0.dist-info/WHEEL
neon_transformers-1.0.0.dist-info/top_level.txt
neon_transformers-1.0.0.dist-info/RECORD
