Metadata-Version: 2.1
Name: neon-transformers
Version: 1.0.0
Home-page: https://github.com/NeonGeckoCom/neon-transformers
Author: Neongecko
Author-email: developers@neon.ai
License: BSD-3-Clause
Keywords: ovos neon plugin
License-File: LICENSE.md
Requires-Dist: ovos-plugin-manager>=0.0.18,~=0.0
Requires-Dist: SpeechRecognition~=3.8
Requires-Dist: ovos-config>=0.0.4,~=0.0
Requires-Dist: ovos-utils>=0.0.23,~=0.0
